cmagic/__init__.py
cmagic/_magic.c
cmagic/_magic.cpython-35m-x86_64-linux-gnu.so
cmagic/_magic.pyi
cmagic/py.typed
cmagic/utils.py
cmagic/version.py
cmagic-1.0.0.dist-info/LICENSE
cmagic-1.0.0.dist-info/METADATA
cmagic-1.0.0.dist-info/WHEEL
cmagic-1.0.0.dist-info/top_level.txt
cmagic-1.0.0.dist-info/RECORD
cmagic.libs/libmagic-a2a5eb8f.so.1.0.0
cmagic.libs/libz-d8a329de.so.1.2.7
