Metadata-Version: 2.1
Name: cmagic
Version: 1.0.0
Summary: Python wrapper for libmagic
Home-page: https://github.com/mosquito/cmagic/
Author: Dmitry Orlov <me@mosquito.su>
Author-email: me@mosquito.su
License: Apache Software License
Project-URL: Say Thanks!, https://saythanks.io/to/me%40mosquito.su
Project-URL: Documentation, https://github.com/mosquito/cmagic/
Project-URL: Source, https://github.com/mosquito/cmagic/
Project-URL: Tracker, https://github.com/mosquito/cmagic/issues
Platform: UNKNOWN
Classifier: License :: OSI Approved :: Apache Software License
Classifier: Topic :: Software Development
Classifier: Topic :: Software Development :: Libraries
Classifier: Intended Audience :: Developers
Classifier: Natural Language :: English
Classifier: Operating System :: MacOS
Classifier: Operating System :: POSIX
Classifier: Operating System :: Microsoft
Classifier: Programming Language :: Python
Classifier: Programming Language :: Python :: 3
Classifier: Programming Language :: Python :: 3.5
Classifier: Programming Language :: Python :: 3.6
Classifier: Programming Language :: Python :: 3.7
Classifier: Programming Language :: Python :: 3.8
Classifier: Programming Language :: Python :: Implementation :: CPython
Requires-Python: >=3.5.*, <4
Provides-Extra: develop
Requires-Dist: pytest ; extra == 'develop'
Requires-Dist: pytest-cov ; extra == 'develop'
